np_services/__init__.py
np_services/open_ephys.py
np_services/protocols.py
np_services/proxies.py
np_services/stim_computer_theme_changer.py
np_services/utils.py
np_services/resources/__init__.py
np_services/resources/mvr_connector.py
np_services/resources/zro.py
np_services/scripts/pretest.py
np_services-0.1.73.dist-info/METADATA
np_services-0.1.73.dist-info/WHEEL
np_services-0.1.73.dist-info/entry_points.txt
np_services-0.1.73.dist-info/top_level.txt
np_services-0.1.73.dist-info/RECORD
