Metadata-Version: 2.4
Name: np-services
Version: 0.1.73
Summary: Tools for interfacing with devices and services used in Mindscope Neuropixels experiments at the Allen Institute.
Author-email: bjhardcastle <ben.hardcastle@alleninstitute.org>
Classifier: Programming Language :: Python :: 3
Classifier: License :: OSI Approved :: MIT License
Classifier: Operating System :: OS Independent
Requires-Python: <4.0,>=3.11
Requires-Dist: requests<3,>=2
Requires-Dist: np-session>=0.6.40
Requires-Dist: pyzmq
Requires-Dist: fabric<3.0,>=2.7
Requires-Dist: pandas>=2.0
Requires-Dist: h5py<4.0.0,>=3.8.0
Requires-Dist: np-config>=0.4.17
Requires-Dist: tables<4.0.0,>=3.8.0
Requires-Dist: npc-sync>=0.1.13
Requires-Dist: npc-stim>=0.1.5
Requires-Dist: npc-mvr>=0.1.2
